tiff_dumper/cli.py
tiff_dumper/config_file.py
tiff_dumper/stores.py
tiff_dumper/tiff_dumper.py
tiff_dumper-0.1.0.dist-info/LICENSE
tiff_dumper-0.1.0.dist-info/METADATA
tiff_dumper-0.1.0.dist-info/WHEEL
tiff_dumper-0.1.0.dist-info/entry_points.txt
tiff_dumper-0.1.0.dist-info/RECORD
