Metadata-Version: 2.1
Name: tiff-dumper
Version: 0.1.0
Summary: Benchmark python coroutines in various ways
License: apache
Author: geospatial-jeff
Author-email: geospatialjeff@gmail.com
Requires-Python: >=3.11,<4.0
Classifier: License :: Other/Proprietary License
Classifier: Programming Language :: Python :: 3
Classifier: Programming Language :: Python :: 3.11
Classifier: Programming Language :: Python :: 3.12
Classifier: Programming Language :: Python :: 3.13
Requires-Dist: PyYAML (>=6.0.2,<7.0.0)
Requires-Dist: anyio (>=4.9.0,<5.0.0)
Requires-Dist: async-tiff (==0.1.0)
Requires-Dist: click (>=8.2.1,<9.0.0)
Requires-Dist: obstore (==0.6.0)
Requires-Dist: pandas (>=2.2.3,<3.0.0)
Requires-Dist: pyarrow (>=20.0.0,<21.0.0)
Requires-Dist: pydantic (>=2.11.5,<3.0.0)
